rocketleague/__init__.py
rocketleague-0.0.1.dist-info/METADATA
rocketleague-0.0.1.dist-info/WHEEL
rocketleague-0.0.1.dist-info/top_level.txt
rocketleague-0.0.1.dist-info/RECORD
