Metadata-Version: 2.1
Name: rocketleague
Version: 0.0.1
Summary: A soon-to-be API wrapper for Rocket League's public API (soon tm).
Author-email: "Tanner B. Corcoran" <tannerbcorcoran@gmail.com>
Project-URL: Homepage, https://github.com/tanrbobanr/rocketleague
Classifier: Programming Language :: Python :: 3
Classifier: License :: OSI Approved :: MIT License
Classifier: Operating System :: OS Independent
Requires-Python: >=3.7
